README.md
setup.py
memorylib/__init__.py
memorylib.egg-info/PKG-INFO
memorylib.egg-info/SOURCES.txt
memorylib.egg-info/dependency_links.txt
memorylib.egg-info/top_level.txt